sqlreader/__init__.py
sqlreader/sqlreader.py
sqlreader-0.1.3.dist-info/LICENSE
sqlreader-0.1.3.dist-info/METADATA
sqlreader-0.1.3.dist-info/WHEEL
sqlreader-0.1.3.dist-info/top_level.txt
sqlreader-0.1.3.dist-info/RECORD
