Metadata-Version: 2.1
Name: sqlreader
Version: 0.1.3
Summary: Simple package to read sql files
Home-page: https://github.com/sidqdev/sqlreader
Author: Sidq
Author-email: dimax258223@gmail.com
License: UNKNOWN
Platform: UNKNOWN
Classifier: Programming Language :: Python :: 3.8
Classifier: License :: OSI Approved :: MIT License
Classifier: Operating System :: OS Independent
Requires-Python: >=3.6
License-File: LICENSE
